easy_gui_jupyter/__init__.py
easy_gui_jupyter/easy_gui_jupyter.py
easy_gui_jupyter-2024.5.28.dist-info/LICENSE.txt
easy_gui_jupyter-2024.5.28.dist-info/METADATA
easy_gui_jupyter-2024.5.28.dist-info/WHEEL
easy_gui_jupyter-2024.5.28.dist-info/RECORD
